ffenc/__about__.py
ffenc/__init__.py
ffenc/cli.py
ffenc/crypto.py
ffenc-0.0.1.dist-info/METADATA
ffenc-0.0.1.dist-info/WHEEL
ffenc-0.0.1.dist-info/entry_points.txt
ffenc-0.0.1.dist-info/licenses/LICENSE.txt
ffenc-0.0.1.dist-info/RECORD
