Metadata-Version: 2.4
Name: ffenc
Version: 0.0.1
Project-URL: Documentation, https://github.com/Hao Wu/ffenc#readme
Project-URL: Issues, https://github.com/Hao Wu/ffenc/issues
Project-URL: Source, https://github.com/Hao Wu/ffenc
Author-email: Hao Wu <haowu@dataset.sh>
License-Expression: MIT
License-File: LICENSE.txt
Classifier: Development Status :: 4 - Beta
Classifier: Programming Language :: Python
Classifier: Programming Language :: Python :: 3.8
Classifier: Programming Language :: Python :: 3.9
Classifier: Programming Language :: Python :: 3.10
Classifier: Programming Language :: Python :: 3.11
Classifier: Programming Language :: Python :: 3.12
Classifier: Programming Language :: Python :: Implementation :: CPython
Classifier: Programming Language :: Python :: Implementation :: PyPy
Requires-Python: >=3.8
Requires-Dist: click>=8.1.0
Requires-Dist: cryptography>=41.0.0
